promptwiz/__init__.py
promptwiz/client.py
promptwiz/query.py
promptwiz-0.0.5.dist-info/METADATA
promptwiz-0.0.5.dist-info/WHEEL
promptwiz-0.0.5.dist-info/top_level.txt
promptwiz-0.0.5.dist-info/RECORD
