Metadata-Version: 2.1
Name: promptwiz
Version: 0.0.5
Summary: PromptWiz API
Home-page: 
Author: PromptWiz
Author-email: contact@promptwiz.co.uk
License: Apache 2.0
Keywords: PromptWiz,PromptWiz API
Requires-Dist: requests
Requires-Dist: httpx
